timeseries_methods/__init__.py
timeseries_methods/compute.py
timeseries_methods/const.py
timeseries_methods/download.py
timeseries_methods/powercurves/DTU_10MW_178_RWT_v1.csv
timeseries_methods/powercurves/IEA_10MW_198_RWT.csv
timeseries_methods/powercurves/IEA_15MW_240_RWT.csv
timeseries_methods/powercurves/NREL_5MW_126_RWT_corrected.csv
timeseries_methods/powercurves/wind_powercurves_tradewind.csv
timeseries_methods/sample.py
timeseries_methods-0.1.0.dist-info/METADATA
timeseries_methods-0.1.0.dist-info/WHEEL
timeseries_methods-0.1.0.dist-info/RECORD
